{
    "type": "AdvancedStatsPanel",
    "name": "ModRune16Panel",
    "fields": {
        "defaultWidget": "ScrollBar",
        "priority": 9004,
        "fitToParent": true
    },
    "children": [
        {
            "type": "RectangleWidget",
            "name": "Background",
            "fields": {
                "fitToScreen": true,
                "color": [
                    0,
                    0,
                    0,
                    0.5
                ]
            },
            "children": [
                {
                    "type": "ClickCatcherWidget",
                    "name": "catcher",
                    "fields": {
                        "fitToParent": true
                    }
                },
                {
                    "type": "Widget",
                    "name": "Anchor",
                    "fields": {
                        "anchor": {
                            "x": 0.5,
                            "y": 0.5
                        },
                        "rect": "$SettingsPanelAnchorRect"
                    },
                    "children": [
                        {
                            "type": "ImageWidget",
                            "name": "Background",
                            "fields": {
                                "filename": "\\PANEL\\Options\\FrontEndOptionsBG"
                            }
                        },
                        {
                            "type": "TextBoxWidget",
                            "name": "Title",
                            "fields": {
                                "rect": {
                                    "x": 0,
                                    "y": 45,
                                    "width": 1950,
                                    "height": 103
                                },
                                "text": "埃歐 Io #16",
                                "style": "$StyleTitleBlock"
                            }
                        },
                        {
                            "type": "ButtonWidget",
                            "name": "CloseButton",
                            "fields": {
                                "rect": {
                                    "x": 1868,
                                    "y": 8
                                },
                                "filename": "PANEL\\closebtn_4x",
                                "onClickMessage": "PanelManager:ClosePanel:ModRune16Panel",
                                "hoveredFrame": 3,
                                "tooltipString": "@strClose",
                                "sound": "cursor_close_window_hd"
                            }
                        },
                        {
                            "type": "ScrollControllerWidget",
                            "name": "ScrollController",
                            "fields": {
                                "rect": "$ModSeconderyScrollBarRect",
                                "anchor": {
                                    "x": 1
                                },
                                "upArrowFilepath": "FrontEnd\\HD\\Final\\FrontEnd_ScrollUpBtn",
                                "downArrowFilepath": "FrontEnd\\HD\\Final\\FrontEnd_ScrollDownBtn",
                                "barFilepath": "PauseMenu\\VerticalIndicator",
                                "viewName": "ScrollView",
                                "wheelScrollSound": "cursor_scroll_hd",
                                "buttonScrollSound": "cursor_scroll_hd"
                            }
                        },
                        {
                            "type": "ScrollViewWidget",
                            "name": "ScrollView",
                            "fields": {
                                "rect": "$ModSeconderyRect",
                                "scrollControllerName": "ScrollController"
                            },
                            "children": [
                                {
                                    "type": "TableWidget",
                                    "name": "MRList",
                                    "fields": {
                                        "columns": [
                                            {
                                                "width": 550,
                                                "alignment": {
                                                    "h": "fit",
                                                    "v": "fit"
                                                }
                                            },
                                            {
                                                "width": 750,
                                                "alignment": {
                                                    "h": "fit",
                                                    "v": "fit"
                                                }
                                            },
                                            {
                                                "width": 400,
                                                "alignment": {
                                                    "h": "fit",
                                                    "v": "fit"
                                                }
                                            },
                                            {
                                                "width": 50,
                                                "alignment": {
                                                    "h": "center",
                                                    "v": "center"
                                                }
                                            }
                                        ],
                                        "rowHeight": "$ModTableRowHeight"
                                    },
                                    "children": [
                                        {
                                            "type": "TableRowWidget",
                                            "name": "MRItem",
                                            "children": [
                                                {
                                                    "type": "TextBoxWidget",
                                                    "name": "MRName",
                                                    "fields": {
                                                        "text": "符文之語",
                                                        "style": "$StyleModGold"
                                                    }
                                                },
                                                {
                                                    "type": "TextBoxWidget",
                                                    "name": "MRBase",
                                                    "fields": {
                                                        "text": "底材",
                                                        "style": "$StyleModWhite"
                                                    }
                                                },
                                                {
                                                    "type": "TextBoxWidget",
                                                    "name": "MRRune",
                                                    "fields": {
                                                        "text": "符文",
                                                        "style": "$StyleModYellow"
                                                    }
                                                }
                                            ]
                                        },
                                        {
                                            "type": "TableRowWidget",
                                            "name": "MRItem",
                                            "children": [
                                                {
                                                    "type": "TextBoxWidget",
                                                    "name": "MRName",
                                                    "fields": {
                                                        "text": "黑錘(Black)",
                                                        "style": "$StyleModGold"
                                                    }
                                                },
                                                {
                                                    "type": "TextBoxWidget",
                                                    "name": "MRBase",
                                                    "fields": {
                                                        "text": "3S Club,Hammer,Mace",
                                                        "style": "$StyleModWhite"
                                                    }
                                                },
                                                {
                                                    "type": "TextBoxWidget",
                                                    "name": "MRRune",
                                                    "fields": {
                                                        "text": "10, 16, 4",
                                                        "style": "$StyleModYellow"
                                                    }
                                                },
                                                {
                                                    "type": "FocusableWidget",
                                                    "name": "MRButton",
                                                    "fields": {
                                                        "fitToParent": true,
                                                        "tooltipString": "ÿc4黑色(Black)\nÿc3+120% 增強傷害\n40% 造成壓碎性打擊的概率\n+200 準確率\n+3-14 冰冷傷害, 3 秒持續時間\n+10 體力\n15% 增加攻擊速度\n擊退\n法術傷害減少 2\n等級 4 屍體爆炸 (12 次)",
                                                        "tooltipStyle": {
                                                            "fontStyle": {
                                                                "options": {
                                                                    "newlineHandling": "standard"
                                                                }
                                                            }
                                                        }
                                                    }
                                                }
                                            ]
                                        },
                                        {
                                            "type": "TableRowWidget",
                                            "name": "MRItem",
                                            "children": [
                                                {
                                                    "type": "TextBoxWidget",
                                                    "name": "MRName",
                                                    "fields": {
                                                        "text": "精神錯亂(Delirium)",
                                                        "style": "$StyleModGold"
                                                    }
                                                },
                                                {
                                                    "type": "TextBoxWidget",
                                                    "name": "MRBase",
                                                    "fields": {
                                                        "text": "3S Helm",
                                                        "style": "$StyleModWhite"
                                                    }
                                                },
                                                {
                                                    "type": "TextBoxWidget",
                                                    "name": "MRRune",
                                                    "fields": {
                                                        "text": "20, 24, 16",
                                                        "style": "$StyleModYellow"
                                                    }
                                                },
                                                {
                                                    "type": "FocusableWidget",
                                                    "name": "MRButton",
                                                    "fields": {
                                                        "fitToParent": true,
                                                        "tooltipString": "ÿc4迪勒瑞姆(Delirium)\nÿc31% 概率當被擊中時施放出 50 級 迪勒瑞姆(stun)\n6% 概率當被擊中時施放出 14級 心靈爆震\n14% 概率當被擊中時施放出 13級 毒牙\n11% 概率擊中敵人時施放出 18級 迷亂\n+2 級所有技能\n+261 防禦力\n+10 活力\n50% 得到額外金錢\n25% 提升魔法裝備出現概率\n17級 吸引 (60 次)",
                                                        "tooltipStyle": {
                                                            "fontStyle": {
                                                                "options": {
                                                                    "newlineHandling": "standard"
                                                                }
                                                            }
                                                        }
                                                    }
                                                }
                                            ]
                                        },
                                        {
                                            "type": "TableRowWidget",
                                            "name": "MRItem",
                                            "children": [
                                                {
                                                    "type": "TextBoxWidget",
                                                    "name": "MRName",
                                                    "fields": {
                                                        "text": "夢境(Dream)",
                                                        "style": "$StyleModGold"
                                                    }
                                                },
                                                {
                                                    "type": "TextBoxWidget",
                                                    "name": "MRBase",
                                                    "fields": {
                                                        "text": "3S Helm,Any Shield",
                                                        "style": "$StyleModWhite"
                                                    }
                                                },
                                                {
                                                    "type": "TextBoxWidget",
                                                    "name": "MRRune",
                                                    "fields": {
                                                        "text": "16, 31, 21",
                                                        "style": "$StyleModYellow"
                                                    }
                                                },
                                                {
                                                    "type": "FocusableWidget",
                                                    "name": "MRButton",
                                                    "fields": {
                                                        "fitToParent": true,
                                                        "tooltipString": "ÿc4夢境(Dream)\nÿc310% 概率當被擊中時施放出 15級 迷亂\nÿc8當裝備後擁有 15級 神聖衝擊靈氣\nÿc9+20-30% 再度快速攻擊ÿcU(變動)\nÿc3330%增強防禦\n+150-220 防禦 ÿcU(變動)\nÿc3+10 體力\n+50 生命\nÿc9+0-61 法力(角色等級乘 0.625)\n所有抗性 +5-20(變動)\nÿc312-25% 更佳取得魔法裝備 ÿcU(變動)\nÿcO重要屬性：15級神聖沖擊光環\n其他亮點：30FHR、20RES、0.625MANA每級\n美中不足：缺-LR\nÿcC底材推薦\nÿc8骸骨面罩：STR需求和DEF較平衡的頭盔\n巨魔骨盾：DEF最高的精華輕盾，適合給VIT型的雙夢SOR\n亥伯龍盾：格擋率最高的通用盾中DEF最高的，適合給BLOCK型的雙夢SOR\n神聖小盾：格擋率最高的PAL盾\n其他：神聖輕圓盾是沒有神聖小盾時的次選擇",
                                                        "tooltipStyle": {
                                                            "fontStyle": {
                                                                "options": {
                                                                    "newlineHandling": "standard"
                                                                }
                                                            }
                                                        }
                                                    }
                                                }
                                            ]
                                        },
                                        {
                                            "type": "TableRowWidget",
                                            "name": "MRItem",
                                            "children": [
                                                {
                                                    "type": "TextBoxWidget",
                                                    "name": "MRName",
                                                    "fields": {
                                                        "text": "記憶(Memory)",
                                                        "style": "$StyleModGold"
                                                    }
                                                },
                                                {
                                                    "type": "TextBoxWidget",
                                                    "name": "MRBase",
                                                    "fields": {
                                                        "text": "4S Staff",
                                                        "style": "$StyleModWhite"
                                                    }
                                                },
                                                {
                                                    "type": "TextBoxWidget",
                                                    "name": "MRRune",
                                                    "fields": {
                                                        "text": "17, 16, 12, 5",
                                                        "style": "$StyleModYellow"
                                                    }
                                                },
                                                {
                                                    "type": "FocusableWidget",
                                                    "name": "MRButton",
                                                    "fields": {
                                                        "fitToParent": true,
                                                        "tooltipString": "ÿc4回憶(Memory)\nÿc3+3 法師技能\n33% 高速施展速度\n增加法力上限 20%\n+3 能量護盾 (限法師使用)\n+2 靜態力場 (限法師使用)\n+10 精力\n+10 體力\n+9 最小傷害\n-25% 目標防禦\n法術傷害減少 7\n+50% 防禦強化",
                                                        "tooltipStyle": {
                                                            "fontStyle": {
                                                                "options": {
                                                                    "newlineHandling": "standard"
                                                                }
                                                            }
                                                        }
                                                    }
                                                }
                                            ]
                                        },
                                        {
                                            "type": "TableRowWidget",
                                            "name": "MRItem",
                                            "children": [
                                                {
                                                    "type": "TextBoxWidget",
                                                    "name": "MRName",
                                                    "fields": {
                                                        "text": "執念(Obsession)",
                                                        "style": "$StyleModGold"
                                                    }
                                                },
                                                {
                                                    "type": "TextBoxWidget",
                                                    "name": "MRBase",
                                                    "fields": {
                                                        "text": "6S Staff",
                                                        "style": "$StyleModWhite"
                                                    }
                                                },
                                                {
                                                    "type": "TextBoxWidget",
                                                    "name": "MRRune",
                                                    "fields": {
                                                        "text": "33, 24, 20, 17, 16, 4",
                                                        "style": "$StyleModYellow"
                                                    }
                                                },
                                                {
                                                    "type": "FocusableWidget",
                                                    "name": "MRButton",
                                                    "fields": {
                                                        "fitToParent": true,
                                                        "tooltipString": "ÿc4執念(Obsession)\nÿc3無法損壞\n24% 幾率在被擊中時施展 等級10 削弱\n+4 所有技能\n+65% 施法速度\n+60% 快速打擊恢復\n擊退\n+10 活力\n+10能量\n最大生命值增加 15-25%\n法力再生 +15-30%\n全抗性 +60-70\n從怪物身上獲得 75%額外金幣\n獲得魔法物品的幾率提高 30%\n（2.4天梯新增）",
                                                        "tooltipStyle": {
                                                            "fontStyle": {
                                                                "options": {
                                                                    "newlineHandling": "standard"
                                                                }
                                                            }
                                                        }
                                                    }
                                                }
                                            ]
                                        },
                                        {
                                            "type": "TableRowWidget",
                                            "name": "MRItem",
                                            "children": [
                                                {
                                                    "type": "TextBoxWidget",
                                                    "name": "MRName",
                                                    "fields": {
                                                        "text": "驕傲(Pride)",
                                                        "style": "$StyleModGold"
                                                    }
                                                },
                                                {
                                                    "type": "TextBoxWidget",
                                                    "name": "MRBase",
                                                    "fields": {
                                                        "text": "4S Polearm,Spear",
                                                        "style": "$StyleModWhite"
                                                    }
                                                },
                                                {
                                                    "type": "TextBoxWidget",
                                                    "name": "MRRune",
                                                    "fields": {
                                                        "text": "32, 29, 16, 28",
                                                        "style": "$StyleModYellow"
                                                    }
                                                },
                                                {
                                                    "type": "FocusableWidget",
                                                    "name": "MRButton",
                                                    "fields": {
                                                        "fitToParent": true,
                                                        "tooltipString": "ÿc4驕傲(Pride)\nÿc325% 機率受攻擊時施展等級 17 火牆\nÿc8等級 16-20 專註靈氣賦予 ÿcU(變動)\nÿc9+260-300% 額外攻擊準確率 ÿcU(變動)\nÿc3+1-99% 對惡魔傷害 (依角色等級乘1)\n增加 50-280 閃電傷害\nÿc920% 致命攻擊\nÿc3擊中使目標目盲\n冰凍目標 +3\n+10 體力\n生命補滿 +8\n+1-185% 額外金錢取自怪物 (依角色等級乘1.875)\nÿcO重要屬性：20級專註光環\n其他亮點：20DS、300%AR\n美中不足：有致盲\n專註光環能極大地提高傷害，但本身沒有ED加成且會碎屍\n一般只給物理弓AMA的PET使用，夠土豪的純招NEC也能用來做鋼鐵石魔\nÿcC底材推薦\nÿc8鮫尾巨斧：一般不看重PET的DPS，需要的是高攻速觸發效果控場\n銳利之斧：沒有鮫尾的次選擇\n巨長斧：最通用的底材，可惜與無限、眼光等更常用的符文之語沖突\n鐮刀：在有攻擊反噬的版本裏，最低的傷害可以防止自殺\n其他：神秘之斧也能作為候選，只是攻速較慢",
                                                        "tooltipStyle": {
                                                            "fontStyle": {
                                                                "options": {
                                                                    "newlineHandling": "standard"
                                                                }
                                                            }
                                                        }
                                                    }
                                                }
                                            ]
                                        },
                                        {
                                            "type": "TableRowWidget",
                                            "name": "MRItem",
                                            "children": [
                                                {
                                                    "type": "TextBoxWidget",
                                                    "name": "MRName",
                                                    "fields": {
                                                        "text": "不屈意志(Unbending Will)",
                                                        "style": "$StyleModGold"
                                                    }
                                                },
                                                {
                                                    "type": "TextBoxWidget",
                                                    "name": "MRBase",
                                                    "fields": {
                                                        "text": "6S Sword",
                                                        "style": "$StyleModWhite"
                                                    }
                                                },
                                                {
                                                    "type": "TextBoxWidget",
                                                    "name": "MRRune",
                                                    "fields": {
                                                        "text": "19, 16, 6, 2, 1, 15",
                                                        "style": "$StyleModYellow"
                                                    }
                                                },
                                                {
                                                    "type": "FocusableWidget",
                                                    "name": "MRButton",
                                                    "fields": {
                                                        "fitToParent": true,
                                                        "tooltipString": "ÿc4不屈意志(Unbending Will)\nÿc3攻擊有 18% 幾率施展18級嘲諷\n+3 戰鬥技能（僅限野蠻人）\n+20-30% 攻速\n+300-350% 增強傷害\n+9 最大傷害\n+50 命中率（AR）\n+75% 對不死者傷害\n 對不死者 +50命中率\n每次命中偷取 8-10% 生命\n阻止怪物治療\n+10 力量\n+10 活力\n傷害減少 8\n+1 光照範圍\n需求 -20%\n（2.4天梯新增）",
                                                        "tooltipStyle": {
                                                            "fontStyle": {
                                                                "options": {
                                                                    "newlineHandling": "standard"
                                                                }
                                                            }
                                                        }
                                                    }
                                                }
                                            ]
                                        },
                                        {
                                            "type": "TableRowWidget",
                                            "name": "MRItem",
                                            "children": [
                                                {
                                                    "type": "TextBoxWidget",
                                                    "name": "MRName",
                                                    "fields": {
                                                        "text": "蒼白(White)",
                                                        "style": "$StyleModGold"
                                                    }
                                                },
                                                {
                                                    "type": "TextBoxWidget",
                                                    "name": "MRBase",
                                                    "fields": {
                                                        "text": "2S Wand",
                                                        "style": "$StyleModWhite"
                                                    }
                                                },
                                                {
                                                    "type": "TextBoxWidget",
                                                    "name": "MRRune",
                                                    "fields": {
                                                        "text": "14, 16",
                                                        "style": "$StyleModYellow"
                                                    }
                                                },
                                                {
                                                    "type": "FocusableWidget",
                                                    "name": "MRButton",
                                                    "fields": {
                                                        "fitToParent": true,
                                                        "tooltipString": "ÿc4白色(White)\nÿc3擊中使怪物逃跑 25%\n+10 體力\nÿc8+3 毒素和白骨技能 (限死靈法師)\nÿc3+3 白骨裝甲 (限死靈法師)\n+2 骨矛 (限死靈法師)\nÿc9+4 支配骷髏 (限死靈法師)\nÿc3法術傷害減少 4\nÿc820% 高速施法\nÿc3+13 法力\nÿcO美中不足：低MANA\nPVC中最適合純骨NEC的武器，也能成為毒NEC的過渡品\nÿcC底材推薦\nÿc8骨杖：白色在PK中多被OAK取代，而骨魂在PVC中也很少使用，所以附帶詛咒的用途更廣\n其他：附帶有3骨矛的2孔NEC杖都有做白色的價值",
                                                        "tooltipStyle": {
                                                            "fontStyle": {
                                                                "options": {
                                                                    "newlineHandling": "standard"
                                                                }
                                                            }
                                                        }
                                                    }
                                                }
                                            ]
                                        }
                                    ]
                                }
                            ]
                        }
                    ]
                }
            ]
        }
    ]
}